py3_execute/__init__.py
py3_execute/_cmd.py
py3_execute/js.py
py3_execute-0.0.5.dist-info/METADATA
py3_execute-0.0.5.dist-info/WHEEL
py3_execute-0.0.5.dist-info/licenses/LICENSE
py3_execute-0.0.5.dist-info/RECORD
