Metadata-Version: 2.4
Name: py3-execute
Version: 0.0.5
Summary: python3 execute
License-File: LICENSE
Author: mathewgeola
Author-email: mathewgeola@gmail.com
Requires-Python: >=3.12
Classifier: Programming Language :: Python :: 3
Classifier: Programming Language :: Python :: 3.12
Classifier: Programming Language :: Python :: 3.13
Classifier: Programming Language :: Python :: 3.14
Requires-Dist: mini-racer (>=0.14.0,<0.15.0)
Requires-Dist: orjson (>=3.11.5,<4.0.0)
Requires-Dist: py3-logger (>=0.0.7,<0.0.8)
Requires-Dist: pyexecjs (>=1.5.1,<2.0.0)
